[{"id":4,"name":"Ajith kumar","age":38,"city":"Namakkal"},{"id":11,"name":"Meena","age":30,"city":"Madurai"},{"id":12,"name":"John","age":28,"city":"Coimbatore"},{"id":13,"name":"Priya","age":35,"city":"Trichy"},{"id":14,"name":"Vijay","age":50,"city":"Vellore"},{"id":15,"name":"Anitha","age":40,"city":"Salem"},{"id":16,"name":"Krishna","age":29,"city":"Chennai"},{"id":17,"name":"Deepa","age":18,"city":"Bangalore"},{"id":18,"name":"Raj","age":55,"city":"Chennai"},{"id":19,"name":"Arun","age":32,"city":"Salem"},{"id":20,"name":"Shivani","age":26,"city":"Erode"},{"id":1721399710649,"name":"yyy","age":"46","city":"4656"},{"id":1721399741861,"name":"Sridhar ","age":"23","city":"Chennai"},{"id":1721400870752,"name":"gghh","age":"7","city":"ghuhuc"}]